ansible_inventory_grapher-2.3.0.data/scripts/ansible-inventory-grapher
ansible_inventory_grapher-2.3.0.dist-info/DESCRIPTION.rst
ansible_inventory_grapher-2.3.0.dist-info/METADATA
ansible_inventory_grapher-2.3.0.dist-info/RECORD
ansible_inventory_grapher-2.3.0.dist-info/WHEEL
ansible_inventory_grapher-2.3.0.dist-info/metadata.json
ansible_inventory_grapher-2.3.0.dist-info/top_level.txt
ansibleinventorygrapher/__init__.py
ansibleinventorygrapher/version.py
